positor/__init__.py
positor/__main__.py
positor/images.py
positor/models.py
positor/positions.py
positor/positor.py
positor/stt_audio.py
positor/stt_stabilization.py
positor/stt_word_level.py
positor-0.6.1.dist-info/LICENSE
positor-0.6.1.dist-info/METADATA
positor-0.6.1.dist-info/WHEEL
positor-0.6.1.dist-info/entry_points.txt
positor-0.6.1.dist-info/top_level.txt
positor-0.6.1.dist-info/RECORD
