Metadata-Version: 2.1
Name: positor
Version: 0.6.1
Summary: Utilities for digital archives.
Home-page: https://github.com/pragmar/positor
Author: pragmar
License: MIT
Requires-Python: >=3.9,<3.11
License-File: LICENSE
Requires-Dist: piexif >=1.1.0
Requires-Dist: colorama >=0.4.0
Requires-Dist: whisper.ai >=1.0.0
Requires-Dist: Pillow >=8.0.0
